{
    "asset": {
        "format": "jpg",
        "id": "56c3244710ed47e66ca6da4b3f4ff196",
        "name": "_D30_120.jpg",
        "path": "file:D:/%E5%A4%A7%E4%B8%89%E4%B8%8B/%E5%BD%B1%E5%83%8F%E5%88%86%E6%9E%90/Project%203/project3/fingernail/fingernail/_D30_120.jpg",
        "size": {
            "width": 382,
            "height": 382
        },
        "state": 2,
        "type": 1
    },
    "regions": [
        {
            "id": "votRXyPZp",
            "type": "RECTANGLE",
            "tags": [
                "Fingernails"
            ],
            "boundingBox": {
                "height": 306.47313786097936,
                "width": 241.86057809012277,
                "left": 99.48370762416295,
                "top": 44.96686213902065
            },
            "points": [
                {
                    "x": 99.48370762416295,
                    "y": 44.96686213902065
                },
                {
                    "x": 341.3442857142857,
                    "y": 44.96686213902065
                },
                {
                    "x": 341.3442857142857,
                    "y": 351.44
                },
                {
                    "x": 99.48370762416295,
                    "y": 351.44
                }
            ]
        }
    ],
    "version": "2.2.0"
}